<?xml version="1.0" encoding="UTF-8"?>
<blocks>
  <block refid="02df366a-10cb-4599-b1a2-567387f6aa89">
    <STATIC_heading>
  <headingLevel value="heading"/>
  <text>&lt;p&gt;CHAPTER 7 | &lt;span style="color:#CA500F;"&gt;Urinary System&lt;/span&gt;&lt;/p&gt;</text>
</STATIC_heading>
  </block>
  <block refid="9308ae63-2f0c-485c-b434-7c93b6d34c6b">
    <STATIC_figure>
  <image>chp00007_co007-9780323551472.png</image>
  <imageControls>
    <imageScale value="full-screen"/>
    <imageAlignment value="center"/>
    <enableBorder value="off"/>
    <enableZoom value="on"/>
    <searchableImage value="on"/>
    <legacyErrorLabel/>
  </imageControls>
  <imageCaption/>
  <imageAlt/>
</STATIC_figure>
  </block>
  <block refid="d509cc8d-c6fa-4d66-9a03-70ca6589fade">
    <STATIC_heading>
  <headingLevel value="subheadinga"/>
  <text>&lt;span style="color:#CA500F;"&gt;&lt;strong&gt;Chapter Sections&lt;/strong&gt;&lt;/span&gt;</text>
</STATIC_heading>
  </block>
  <block refid="4c3423a2-1dfe-4a2c-8cbb-2519b958640a">
    <STATIC_text>
  <text>&lt;p&gt;&lt;strong&gt;&lt;a href="000302037190230741.xhtml" data-handler="screen-link" data-handler-handled="true"&gt;Introduction&lt;/a&gt;&lt;br/&gt;&lt;a href="000302038190230741.xhtml" data-handler="screen-link" data-handler-handled="true"&gt;Anatomy of the Major Organs&lt;/a&gt;&lt;br/&gt;&lt;a href="000302039190230741.xhtml" data-handler="screen-link" data-handler-handled="true"&gt;Physiology: How the Kidneys Produce Urine&lt;/a&gt;&lt;br/&gt;&lt;a href="000302040190230741.xhtml" data-handler="screen-link" data-handler-handled="true"&gt;Vocabulary&lt;/a&gt;&lt;br/&gt;&lt;a href="000302041190230741.xhtml" data-handler="screen-link" data-handler-handled="true"&gt;Terminology: Structures, Substances, and Urinary Signs and Symptoms&lt;/a&gt;&lt;br/&gt;&lt;a href="000302042190230741.xhtml" data-handler="screen-link" data-handler-handled="true"&gt;Urinalysis&lt;/a&gt;&lt;br/&gt;&lt;a href="000302043190230741.xhtml" data-handler="screen-link" data-handler-handled="true"&gt;Pathologic Terminology: Kidney, Bladder, and Associated Conditions&lt;/a&gt;&lt;br/&gt;&lt;a href="000302044190230741.xhtml" data-handler="screen-link" data-handler-handled="true"&gt;Laboratory Tests and Clinical Procedures&lt;/a&gt;&lt;br/&gt;&lt;a href="000302045190230741.xhtml" data-handler="screen-link" data-handler-handled="true"&gt;Abbreviations&lt;/a&gt;&lt;br/&gt;&lt;a href="000302046190230741.xhtml" data-handler="screen-link" data-handler-handled="true"&gt;Practical Applications&lt;/a&gt;&lt;br/&gt;&lt;a href="000302047190230741.xhtml" data-handler="screen-link" data-handler-handled="true"&gt;In Person: Kidney Transplant&lt;/a&gt;&lt;br/&gt;&lt;a href="000315281240211918.xhtml" data-handler="screen-link" data-handler-handled="true"&gt;Exercises&lt;/a&gt;&lt;br/&gt;&lt;a href="000302048190230741.xhtml" data-handler="screen-link" data-handler-handled="true"&gt;Pronunciation of Terms&lt;/a&gt;&lt;br/&gt;&lt;a href="000302049190230741.xhtml" data-handler="screen-link" data-handler-handled="true"&gt;Review Sheet&lt;/a&gt;&lt;/strong&gt;&lt;/p&gt;</text>
</STATIC_text>
  </block>
  <block refid="16fb414d-1cca-424e-847c-44ddc2a12683">
    <STATIC_container>
  <text>&lt;p&gt;&lt;span style="color:#CA500F;"&gt;&lt;strong&gt;CHAPTER GOALS&lt;/strong&gt;&lt;/span&gt;&lt;/p&gt;&lt;ul&gt;&lt;li&gt;&lt;span style="color:#3c3c3c;"&gt;Name essential organs of the urinary system and describe their locations and functions.&lt;/span&gt;&lt;/li&gt;&lt;li&gt;&lt;span style="color:#3c3c3c;"&gt;Identify common pathologic conditions affecting the urinary system.&lt;/span&gt;&lt;/li&gt;&lt;li&gt;&lt;span style="color:#3c3c3c;"&gt;Recognize how urinalysis is used and interpreted as a diagnostic test.&lt;/span&gt;&lt;/li&gt;&lt;li&gt;&lt;span style="color:#3c3c3c;"&gt;Define urinary system–related combining forms, prefixes, and suffixes. &lt;/span&gt;&lt;/li&gt;&lt;li&gt;&lt;span style="color:#3c3c3c;"&gt;List and explain laboratory tests, clinical procedures, and abbreviations that pertain to the urinary system.&lt;/span&gt;&lt;/li&gt;&lt;li&gt;&lt;span style="color:#3c3c3c;"&gt;Understand medical terms in their proper contexts, such as medical reports and records.&lt;/span&gt;&lt;/li&gt;&lt;/ul&gt;</text>
  <bgColor value="ececec"/>
</STATIC_container>
  </block>
</blocks>
