<?xml version="1.0" encoding="UTF-8"?>
<blocks>
  <block refid="9ffb4527-b760-4cba-be92-29a333aedd33">
    <STATIC_heading>
  <headingLevel value="heading"/>
  <text>&lt;p&gt;&lt;span style="color:#556B04;"&gt;TERMINOLOGY&lt;/span&gt;&lt;/p&gt;</text>
</STATIC_heading>
  </block>
  <block refid="852be748-7c43-4f8e-bc59-7e089838c219">
    <STATIC_heading>
  <headingLevel value="subheadinga"/>
  <text>&lt;p&gt;&lt;span style="color:#007FAD;"&gt;COMBINING FORMS&lt;/span&gt;&lt;/p&gt;</text>
</STATIC_heading>
  </block>
  <block refid="268e44df-8211-429f-9cb2-04e885357fbe">
    <STATIC_table>
  <text>&lt;table class="c-table js-x-scroll-component" border="1" cellspacing="0" cellpadding="1" style="width: 100%;"&gt;&lt;thead&gt;&lt;tr&gt;&lt;th scope="col" style="text-align: left;"&gt;&lt;span style="color:#556B04;"&gt;&lt;strong&gt;COMBINING FORM&lt;/strong&gt;&lt;/span&gt;&lt;/th&gt;&lt;th scope="col" style="text-align: left;"&gt;&lt;span style="color:#556B04;"&gt;&lt;strong&gt;MEANING&lt;/strong&gt;&lt;/span&gt;&lt;/th&gt;&lt;th scope="col" style="text-align: left;"&gt;&lt;span style="color:#556B04;"&gt;TERMINOLOGY&lt;/span&gt;&lt;/th&gt;&lt;/tr&gt;&lt;/thead&gt;&lt;tbody&gt;&lt;tr&gt;&lt;td&gt;&lt;strong&gt;alveol/o&lt;/strong&gt;&lt;/td&gt;&lt;td&gt;small sac&lt;/td&gt;&lt;td&gt;&lt;u&gt;alveol&lt;/u&gt;ar&lt;br/&gt;&lt;em&gt;Microscopic description of tumor cell arrangement (found in connective tissue tumors).&lt;/em&gt;&lt;/td&gt;&lt;/tr&gt;&lt;tr&gt;&lt;td&gt;&lt;strong&gt;cac/o&lt;/strong&gt;&lt;/td&gt;&lt;td&gt;bad&lt;/td&gt;&lt;td&gt;&lt;u&gt;cac&lt;/u&gt;hexia&lt;br/&gt;&lt;em&gt;General ill health and malnutrition (wasting of muscle and emaciation) associated with chronic, severe disease (-hexia means state or condition).&lt;/em&gt;&lt;/td&gt;&lt;/tr&gt;&lt;tr&gt;&lt;td&gt;&lt;strong&gt;carcin/o&lt;/strong&gt;&lt;/td&gt;&lt;td&gt;cancer, cancerous&lt;/td&gt;&lt;td&gt;&lt;u&gt;carcin&lt;/u&gt;oma in situ&lt;br/&gt;&lt;em&gt;Localized cancer; confined to the site of origin.&lt;/em&gt;&lt;/td&gt;&lt;/tr&gt;&lt;tr&gt;&lt;td&gt;&lt;strong&gt;cauter/o&lt;/strong&gt;&lt;/td&gt;&lt;td&gt;burn, heat&lt;/td&gt;&lt;td&gt;electro&lt;u&gt;cauter&lt;/u&gt;ization&lt;/td&gt;&lt;/tr&gt;&lt;tr&gt;&lt;td&gt;&lt;strong&gt;chem/o&lt;/strong&gt;&lt;/td&gt;&lt;td&gt;chemical, drug&lt;/td&gt;&lt;td&gt;&lt;u&gt;chem&lt;/u&gt;otherapy&lt;/td&gt;&lt;/tr&gt;&lt;tr&gt;&lt;td&gt;&lt;strong&gt;cry/o&lt;/strong&gt;&lt;/td&gt;&lt;td&gt;cold&lt;/td&gt;&lt;td&gt;&lt;u&gt;cry&lt;/u&gt;osurgery&lt;/td&gt;&lt;/tr&gt;&lt;tr&gt;&lt;td&gt;&lt;strong&gt;cyst/o&lt;/strong&gt;&lt;/td&gt;&lt;td&gt;sac of fluid&lt;/td&gt;&lt;td&gt;&lt;u&gt;cyst&lt;/u&gt;ic tumor&lt;/td&gt;&lt;/tr&gt;&lt;tr&gt;&lt;td&gt;&lt;strong&gt;fibr/o&lt;/strong&gt;&lt;/td&gt;&lt;td&gt;fibers&lt;/td&gt;&lt;td&gt;&lt;u&gt;fibr&lt;/u&gt;osarcoma&lt;/td&gt;&lt;/tr&gt;&lt;tr&gt;&lt;td&gt;&lt;strong&gt;follicul/o&lt;/strong&gt;&lt;/td&gt;&lt;td&gt;small glandular sacs&lt;/td&gt;&lt;td&gt;&lt;u&gt;follicul&lt;/u&gt;ar&lt;br/&gt;&lt;em&gt;A microscopic description of cellular arrangement in glandular tumors.&lt;/em&gt;&lt;/td&gt;&lt;/tr&gt;&lt;tr&gt;&lt;td&gt;&lt;strong&gt;fung/i&lt;/strong&gt;&lt;/td&gt;&lt;td&gt;fungus, mushroom&lt;/td&gt;&lt;td&gt;&lt;u&gt;fung&lt;/u&gt;ating tumor&lt;/td&gt;&lt;/tr&gt;&lt;tr&gt;&lt;td&gt;&lt;strong&gt;medull/o&lt;/strong&gt;&lt;/td&gt;&lt;td&gt;soft, inner part&lt;/td&gt;&lt;td&gt;&lt;u&gt;medull&lt;/u&gt;ary tumor&lt;/td&gt;&lt;/tr&gt;&lt;tr&gt;&lt;td&gt;&lt;strong&gt;mucos/o&lt;/strong&gt;&lt;/td&gt;&lt;td&gt;mucous membrane&lt;/td&gt;&lt;td&gt;&lt;u&gt;mucos&lt;/u&gt;itis&lt;/td&gt;&lt;/tr&gt;&lt;tr&gt;&lt;td&gt;&lt;strong&gt;mut/a&lt;/strong&gt;&lt;/td&gt;&lt;td&gt;genetic change&lt;/td&gt;&lt;td&gt;&lt;u&gt;mut&lt;/u&gt;ation&lt;br/&gt;&lt;em&gt;-tion means process.&lt;/em&gt;&lt;/td&gt;&lt;/tr&gt;&lt;tr&gt;&lt;td&gt;&lt;strong&gt;mutagen/o&lt;/strong&gt;&lt;/td&gt;&lt;td&gt;causing genetic change&lt;/td&gt;&lt;td&gt;&lt;u&gt;mutagen&lt;/u&gt;ic&lt;/td&gt;&lt;/tr&gt;&lt;tr&gt;&lt;td&gt;&lt;strong&gt;necr/o&lt;/strong&gt;&lt;/td&gt;&lt;td&gt;death&lt;/td&gt;&lt;td&gt;&lt;u&gt;necr&lt;/u&gt;otic tumor&lt;/td&gt;&lt;/tr&gt;&lt;tr&gt;&lt;td&gt;&lt;strong&gt;neur/o&lt;/strong&gt;&lt;/td&gt;&lt;td&gt;nerve&lt;/td&gt;&lt;td&gt;&lt;u&gt;neuro&lt;/u&gt;fibromatosis&lt;br/&gt;&lt;em&gt;Fibromas are tumors of fibrous connective tissue. Tumors begin in supporting cells of nerves and the myelin sheath around nerve cells. Most tumors are benign but some may become cancerous. It is a genetic disorder occurring in 1 in 3000 births, but some cases arise via spontaneous mutation.&lt;/em&gt;&lt;/td&gt;&lt;/tr&gt;&lt;tr&gt;&lt;td&gt;&lt;strong&gt;onc/o&lt;/strong&gt;&lt;/td&gt;&lt;td&gt;tumor&lt;/td&gt;&lt;td&gt;&lt;u&gt;onc&lt;/u&gt;ology&lt;/td&gt;&lt;/tr&gt;&lt;tr&gt;&lt;td&gt;&lt;strong&gt;papill/o&lt;/strong&gt;&lt;/td&gt;&lt;td&gt;nipple-like&lt;/td&gt;&lt;td&gt;&lt;u&gt;papill&lt;/u&gt;ary&lt;br/&gt;&lt;em&gt;A microscopic description of tumor cell growth.&lt;/em&gt;&lt;/td&gt;&lt;/tr&gt;&lt;tr&gt;&lt;td&gt;&lt;strong&gt;plas/o&lt;/strong&gt;&lt;/td&gt;&lt;td&gt;formation&lt;/td&gt;&lt;td&gt;dys&lt;u&gt;plas&lt;/u&gt;tic&lt;br/&gt;&lt;em&gt;Microscopic description of cells that are highly abnormal but not clearly cancerous. The suffix -tic means pertaining to.&lt;/em&gt;&lt;/td&gt;&lt;/tr&gt;&lt;tr&gt;&lt;td&gt;&lt;strong&gt;ple/o&lt;/strong&gt;&lt;/td&gt;&lt;td&gt;many, more&lt;/td&gt;&lt;td&gt;&lt;u&gt;ple&lt;/u&gt;omorphic&lt;br/&gt;&lt;em&gt;Microscopic description of tumors that are composed of a variety of cells.&lt;/em&gt;&lt;/td&gt;&lt;/tr&gt;&lt;tr&gt;&lt;td&gt;&lt;strong&gt;polyp/o&lt;/strong&gt;&lt;/td&gt;&lt;td&gt;polyp&lt;/td&gt;&lt;td&gt;&lt;u&gt;polyp&lt;/u&gt;oid tumor&lt;br/&gt;&lt;em&gt;The suffix -oid means resembling.&lt;/em&gt;&lt;/td&gt;&lt;/tr&gt;&lt;tr&gt;&lt;td&gt;&lt;strong&gt;prot/o&lt;/strong&gt;&lt;/td&gt;&lt;td&gt;first&lt;/td&gt;&lt;td&gt;&lt;u&gt;prot&lt;/u&gt;ocol&lt;br/&gt;&lt;em&gt;The ending -col, from Latin kolla, means glued page. A protocol is a written plan detailing the procedures to be followed in research or treatment.&lt;/em&gt;&lt;/td&gt;&lt;/tr&gt;&lt;tr&gt;&lt;td&gt;&lt;strong&gt;radi/o&lt;/strong&gt;&lt;/td&gt;&lt;td&gt;rays&lt;/td&gt;&lt;td&gt;radiation&lt;br/&gt;&lt;em&gt;Use of radioactive substances in the diagnosis and treatment of disease. &lt;strong&gt;Irradiation &lt;/strong&gt;is exposure to any form of radiation (ionizing, heat, light, or x-rays).&lt;/em&gt;&lt;/td&gt;&lt;/tr&gt;&lt;tr&gt;&lt;td&gt;&lt;strong&gt;sarc/o&lt;/strong&gt;&lt;/td&gt;&lt;td&gt;flesh, connective&lt;br/&gt;tissue&lt;/td&gt;&lt;td&gt;osteo&lt;u&gt;sarc&lt;/u&gt;oma&lt;/td&gt;&lt;/tr&gt;&lt;tr&gt;&lt;td&gt;&lt;strong&gt;scirrh/o&lt;/strong&gt;&lt;/td&gt;&lt;td&gt;hard&lt;/td&gt;&lt;td&gt;&lt;u&gt;scirrh&lt;/u&gt;ous&lt;br/&gt;&lt;em&gt;Microscopic description of densely packed, fibrous tumor cell composition.&lt;/em&gt;&lt;/td&gt;&lt;/tr&gt;&lt;tr&gt;&lt;td&gt;&lt;strong&gt;xer/o&lt;/strong&gt;&lt;/td&gt;&lt;td&gt;dry&lt;/td&gt;&lt;td&gt;&lt;u&gt;xer&lt;/u&gt; ostomia&lt;/td&gt;&lt;/tr&gt;&lt;/tbody&gt;&lt;/table&gt;</text>
</STATIC_table>
  </block>
  <block refid="feaf5de8-dae6-49b9-8830-28abb9217db9">
    <STATIC_heading>
  <headingLevel value="subheadinga"/>
  <text>&lt;p&gt;&lt;span style="color:#007FAD;"&gt;SUFFIXES&lt;/span&gt;&lt;/p&gt;</text>
</STATIC_heading>
  </block>
  <block refid="2d4c1710-2f39-46ea-a238-0189c11e05a9">
    <STATIC_table>
  <text>&lt;table class="c-table js-x-scroll-component" border="1" cellspacing="0" cellpadding="1" style="width: 100%;"&gt;&lt;thead&gt;&lt;tr&gt;&lt;th scope="col" style="text-align: left;"&gt;&lt;span style="color:#556B04;"&gt;&lt;strong&gt;SUFFIX&lt;/strong&gt;&lt;/span&gt;&lt;/th&gt;&lt;th scope="col" style="text-align: left;"&gt;&lt;span style="color:#556B04;"&gt;MEANING&lt;/span&gt;&lt;/th&gt;&lt;th scope="col" style="text-align: left;"&gt;&lt;span style="color:#556B04;"&gt;TERMINOLOGY&lt;/span&gt;&lt;/th&gt;&lt;/tr&gt;&lt;/thead&gt;&lt;tbody&gt;&lt;tr&gt;&lt;td&gt;&lt;strong&gt;-blastoma&lt;/strong&gt;&lt;/td&gt;&lt;td&gt;immature tumor&lt;/td&gt;&lt;td&gt;&lt;p&gt;retino&lt;u&gt;blastoma&lt;/u&gt;&lt;br/&gt;&lt;em&gt;Childhood cancer arising from immature cells in the retina (posterior, light-sensitive area of the eye).&lt;/em&gt;&lt;/p&gt;&lt;p&gt;neuro&lt;u&gt;blastoma&lt;/u&gt;&lt;br/&gt;&lt;em&gt;This sarcoma of nervous system origin affects infants and children up to the age of 10 years, usually arising in immature tissues of the autonomic nervous system or adrenal medulla.&lt;/em&gt;&lt;/p&gt;&lt;/td&gt;&lt;/tr&gt;&lt;tr&gt;&lt;td&gt;&lt;strong&gt;-genesis&lt;/strong&gt;&lt;/td&gt;&lt;td&gt;formation&lt;/td&gt;&lt;td&gt;carcino&lt;u&gt;genesis&lt;/u&gt;&lt;/td&gt;&lt;/tr&gt;&lt;tr&gt;&lt;td&gt;&lt;strong&gt;-oma&lt;/strong&gt;&lt;/td&gt;&lt;td&gt;mass, tumor&lt;/td&gt;&lt;td&gt;adenocarcin&lt;u&gt;oma&lt;/u&gt;&lt;/td&gt;&lt;/tr&gt;&lt;tr&gt;&lt;td&gt;&lt;strong&gt;-plasia&lt;/strong&gt;&lt;/td&gt;&lt;td&gt;formation, growth&lt;/td&gt;&lt;td&gt;hyper&lt;u&gt;plasia&lt;/u&gt;&lt;/td&gt;&lt;/tr&gt;&lt;tr&gt;&lt;td&gt;&lt;strong&gt;-plasm&lt;/strong&gt;&lt;/td&gt;&lt;td&gt;formation, growth&lt;/td&gt;&lt;td&gt;neo&lt;u&gt;plasm&lt;/u&gt;&lt;/td&gt;&lt;/tr&gt;&lt;tr&gt;&lt;td&gt;&lt;strong&gt;-suppression&lt;/strong&gt;&lt;/td&gt;&lt;td&gt;to stop&lt;/td&gt;&lt;td&gt;myelo&lt;u&gt;suppression&lt;/u&gt;&lt;/td&gt;&lt;/tr&gt;&lt;tr&gt;&lt;td&gt;&lt;strong&gt;-therapy&lt;/strong&gt;&lt;/td&gt;&lt;td&gt;treatment&lt;/td&gt;&lt;td&gt;radio&lt;u&gt;therapy&lt;/u&gt;&lt;br/&gt;&lt;em&gt;Ionizing radiation is used to treat malignancies.&lt;/em&gt;&lt;/td&gt;&lt;/tr&gt;&lt;/tbody&gt;&lt;/table&gt;</text>
</STATIC_table>
  </block>
  <block refid="f9a61df6-6633-4373-a570-a76d16a7fd42">
    <STATIC_heading>
  <headingLevel value="subheadinga"/>
  <text>&lt;p&gt;&lt;span style="color:#007FAD;"&gt;PREFIXES&lt;/span&gt;&lt;/p&gt;</text>
</STATIC_heading>
  </block>
  <block refid="9acbbaa9-f2fe-4378-a208-d7570848a0f3">
    <STATIC_table>
  <text>&lt;table class="c-table js-x-scroll-component" border="1" cellspacing="0" cellpadding="1" style="width: 100%;"&gt;&lt;thead&gt;&lt;tr&gt;&lt;th scope="col" style="text-align: left;"&gt;&lt;span style="color:#556B04;"&gt;PREFIX&lt;/span&gt;&lt;/th&gt;&lt;th scope="col" style="text-align: left;"&gt;&lt;span style="color:#556B04;"&gt;MEANING&lt;/span&gt;&lt;/th&gt;&lt;th scope="col" style="text-align: left;"&gt;&lt;span style="color:#556B04;"&gt;TERMINOLOGY&lt;/span&gt;&lt;/th&gt;&lt;/tr&gt;&lt;/thead&gt;&lt;tbody&gt;&lt;tr&gt;&lt;td&gt;&lt;strong&gt;ana-&lt;/strong&gt;&lt;/td&gt;&lt;td&gt;backward&lt;/td&gt;&lt;td&gt;&lt;u&gt;ana&lt;/u&gt;plasia&lt;/td&gt;&lt;/tr&gt;&lt;tr&gt;&lt;td&gt;&lt;strong&gt;apo-&lt;/strong&gt;&lt;/td&gt;&lt;td&gt;off, away&lt;/td&gt;&lt;td&gt;&lt;u&gt;apo&lt;/u&gt;ptosis&lt;/td&gt;&lt;/tr&gt;&lt;tr&gt;&lt;td&gt;&lt;strong&gt;brachy-&lt;/strong&gt;&lt;/td&gt;&lt;td&gt;short (distance)&lt;/td&gt;&lt;td&gt;&lt;u&gt;brachy&lt;/u&gt;therapy&lt;br/&gt;&lt;em&gt;Radiation delivered in close range to tumor site.&lt;/em&gt;&lt;/td&gt;&lt;/tr&gt;&lt;tr&gt;&lt;td&gt;&lt;p&gt; &lt;/p&gt;&lt;p&gt;&lt;strong&gt;epi-&lt;/strong&gt;&lt;/p&gt;&lt;/td&gt;&lt;td&gt;upon&lt;/td&gt;&lt;td&gt;&lt;u&gt;epi&lt;/u&gt;dermoid&lt;br/&gt;&lt;em&gt;Microscopic description of tumor cells that resemble epidermal tissue.&lt;/em&gt;&lt;/td&gt;&lt;/tr&gt;&lt;tr&gt;&lt;td&gt;&lt;strong&gt;meta-&lt;/strong&gt;&lt;/td&gt;&lt;td&gt;beyond; change&lt;/td&gt;&lt;td&gt;&lt;u&gt;meta&lt;/u&gt;stasis&lt;/td&gt;&lt;/tr&gt;&lt;tr&gt;&lt;td&gt;&lt;strong&gt;neo-&lt;/strong&gt;&lt;/td&gt;&lt;td&gt;new&lt;/td&gt;&lt;td&gt;&lt;u&gt;neo&lt;/u&gt;adjuvant&lt;br/&gt;&lt;em&gt;Adjuvant means to assist or aid. &lt;/em&gt;&lt;img alt="" class="c-inline-icon" data-handler="inline-image" style="vertical-align: middle; width: 16px; height: 16px;" src="../media/icons.png" data-handler-handled="true"/&gt;&lt;/td&gt;&lt;/tr&gt;&lt;tr&gt;&lt;td&gt;&lt;strong&gt;tele-&lt;/strong&gt;&lt;/td&gt;&lt;td&gt;far&lt;/td&gt;&lt;td&gt;&lt;u&gt;tele&lt;/u&gt;therapy&lt;br/&gt;&lt;em&gt;Also called &lt;strong&gt;external beam radiotherapy.&lt;/strong&gt;&lt;/em&gt;&lt;/td&gt;&lt;/tr&gt;&lt;/tbody&gt;&lt;/table&gt;</text>
</STATIC_table>
  </block>
  <block refid="8c17bbfd-89d2-4843-9f97-e977a8843eef">
    <STATIC_text>
  <text>&lt;p&gt;&lt;strong&gt;&lt;img alt="" class="c-inline-icon" data-handler="inline-image" style="vertical-align: middle; width: 16px; height: 16px;" src="../media/icons.png" data-handler-handled="true"/&gt; Neoadjuvant and Adjuvant&lt;/strong&gt;&lt;/p&gt;&lt;p&gt;Don’t confuse these terms.&lt;strong&gt; Neoadjuvant drug therapy&lt;/strong&gt; is delivered &lt;strong&gt;before &lt;/strong&gt;primary treatment, as a first step to shrink a tumor. &lt;strong&gt;Adjuvant drug therapy&lt;/strong&gt; is given &lt;strong&gt;after &lt;/strong&gt;primary treatment to kill possible hidden tumor cells.&lt;/p&gt;</text>
</STATIC_text>
  </block>
</blocks>
